gvasp-0.1.11.dist-info/RECORD
gvasp-0.1.11.dist-info/WHEEL
gvasp-0.1.11.dist-info/entry_points.txt
gvasp-0.1.11.dist-info/top_level.txt
gvasp-0.1.11.dist-info/METADATA
gvasp-0.1.11.dist-info/licenses/LICENSE
gvasp/INCAR
gvasp/slurm.submit
gvasp/config.json
gvasp/__init__.py
gvasp/gvasp-bash-completion.sh
gvasp/UValue.yaml
gvasp/element.yaml
gvasp/main.py
gvasp/common/descriptor.py
gvasp/common/task.py
gvasp/common/plot.py
gvasp/common/error.py
gvasp/common/figure.py
gvasp/common/__init__.py
gvasp/common/setting.py
gvasp/common/encoder.py
gvasp/common/file.py
gvasp/common/utils.py
gvasp/common/calculator.py
gvasp/common/structure.py
gvasp/common/constant.py
gvasp/common/parameter.py
gvasp/common/base.py
gvasp/neb/__init__.py
gvasp/neb/path.py
gvasp/lib/__init__.py
gvasp/lib/dos_cython.cpython-39-darwin.so
gvasp/lib/file_bind.cpython-39-darwin.so
gvasp/lib/base_bind.cpython-39-darwin.so
gvasp/lib/path_cython.cpython-39-darwin.so
