Metadata-Version: 2.4
Name: gvasp
Version: 0.1.11
Summary: A quick post-process for resolve or assistant the VASP calculations
Home-page: https://github.com/Rasic2/gvasp
Author-email: Hui Zhou <1051987201@qq.com>
License:                     GNU GENERAL PUBLIC LICENSE
Classifier: Programming Language :: Python :: 3
Classifier: License :: OSI Approved :: GNU Lesser General Public License v3 (LGPLv3)
Classifier: Operating System :: OS Independent
Requires-Python: >=3.9
License-File: LICENSE
Requires-Dist: pybind11
Requires-Dist: Cython
Requires-Dist: lxml
Requires-Dist: matplotlib
Requires-Dist: numpy
Requires-Dist: pandas
Requires-Dist: pyyaml
Requires-Dist: scipy
Requires-Dist: pytest
Requires-Dist: seekpath
Dynamic: home-page
Dynamic: license-file
